[{"id": "cd066358-0028-11ec-bcad-1e003136597a", "data": [{"text": "มีที่พักไหม", "userDefined": false}], "isTemplate": false, "count": 0, "lang": "th"}, {"id": "cd066402-0028-11ec-bcad-1e003136597a", "data": [{"text": "มีที่พักไหม", "userDefined": false}], "isTemplate": false, "count": 0, "lang": "th"}, {"id": "cd066484-0028-11ec-bcad-1e003136597a", "data": [{"text": "มีที่พักป่าว", "userDefined": false}], "isTemplate": false, "count": 0, "lang": "th"}, {"id": "cd066506-0028-11ec-bcad-1e003136597a", "data": [{"text": "มีที่พักไหมคะ", "userDefined": false}], "isTemplate": false, "count": 0, "lang": "th"}, {"id": "cd066588-0028-11ec-bcad-1e003136597a", "data": [{"text": "มีที่พักไหมครับ", "userDefined": false}], "isTemplate": false, "count": 0, "lang": "th"}, {"id": "cd066600-0028-11ec-bcad-1e003136597a", "data": [{"text": "มีที่พักไหม", "userDefined": false}], "isTemplate": false, "count": 0, "lang": "th"}, {"id": "cd066682-0028-11ec-bcad-1e003136597a", "data": [{"text": "มีหอพักรึเปล่าคะ", "userDefined": false}], "isTemplate": false, "count": 0, "lang": "th"}, {"id": "cd066704-0028-11ec-bcad-1e003136597a", "data": [{"text": "มีหอพักในมอไหม", "userDefined": false}], "isTemplate": false, "count": 0, "lang": "th"}, {"id": "cd06677c-0028-11ec-bcad-1e003136597a", "data": [{"text": "มีหอพักสำหรับนักศึกษามั้ยคะ", "userDefined": false}], "isTemplate": false, "count": 0, "lang": "th"}, {"id": "cd0667fe-0028-11ec-bcad-1e003136597a", "data": [{"text": "ค่าหอเท่าไหร่", "userDefined": false}], "isTemplate": false, "count": 0, "lang": "th"}, {"id": "cd066880-0028-11ec-bcad-1e003136597a", "data": [{"text": "ค่าหอพักราคาเท่าไรคะ", "userDefined": false}], "isTemplate": false, "count": 0, "lang": "th"}, {"id": "cd066902-0028-11ec-bcad-1e003136597a", "data": [{"text": "ค่าหอพักราคาเท่าไรหรอคะ", "userDefined": false}], "isTemplate": false, "count": 0, "lang": "th"}, {"id": "cd066984-0028-11ec-bcad-1e003136597a", "data": [{"text": "ค่าหอราคาเท่าไหร่ครับ", "userDefined": false}], "isTemplate": false, "count": 0, "lang": "th"}, {"id": "cd066a06-0028-11ec-bcad-1e003136597a", "data": [{"text": "ค่าหอเท่าไรคะ", "userDefined": false}], "isTemplate": false, "count": 0, "lang": "th"}, {"id": "cd066a88-0028-11ec-bcad-1e003136597a", "data": [{"text": "ค่าหอเท่าไหร่คะ", "userDefined": false}], "isTemplate": false, "count": 0, "lang": "th"}, {"id": "cd066b00-0028-11ec-bcad-1e003136597a", "data": [{"text": "ค่าหอเท่าไหร", "userDefined": false}], "isTemplate": false, "count": 0, "lang": "th"}, {"id": "cd066b82-0028-11ec-bcad-1e003136597a", "data": [{"text": "ค่าหอเท่าไหร่", "userDefined": false}], "isTemplate": false, "count": 0, "lang": "th"}, {"id": "cd066c04-0028-11ec-bcad-1e003136597a", "data": [{"text": "ขอระเบียบการหอพัก", "userDefined": false}], "isTemplate": false, "count": 0, "lang": "th"}, {"id": "cd066c86-0028-11ec-bcad-1e003136597a", "data": [{"text": "มีหอพักไหม", "userDefined": false}], "isTemplate": false, "count": 0, "lang": "th"}, {"id": "cd066cfe-0028-11ec-bcad-1e003136597a", "data": [{"text": "มีหอพักป่าว", "userDefined": false}], "isTemplate": false, "count": 0, "lang": "th"}, {"id": "cd066d80-0028-11ec-bcad-1e003136597a", "data": [{"text": "มีหอพักไหม", "userDefined": false}], "isTemplate": false, "count": 0, "lang": "th"}, {"id": "cd066df8-0028-11ec-bcad-1e003136597a", "data": [{"text": "มีหอพักให้ป่าว", "userDefined": false}], "isTemplate": false, "count": 0, "lang": "th"}, {"id": "cd066e7a-0028-11ec-bcad-1e003136597a", "data": [{"text": "มีหอพักให้พักไหมคะ", "userDefined": false}], "isTemplate": false, "count": 0, "lang": "th"}, {"id": "cd066efc-0028-11ec-bcad-1e003136597a", "data": [{"text": "มีหอพักป่าว", "userDefined": false}], "isTemplate": false, "count": 0, "lang": "th"}, {"id": "cd066f7e-0028-11ec-bcad-1e003136597a", "data": [{"text": "มีหอพักไหมครับ", "userDefined": false}], "isTemplate": false, "count": 0, "lang": "th"}, {"id": "cd066ff6-0028-11ec-bcad-1e003136597a", "data": [{"text": "ที่นี่มีหอพักไหมคะ", "userDefined": false}], "isTemplate": false, "count": 0, "lang": "th"}, {"id": "cd067078-0028-11ec-bcad-1e003136597a", "data": [{"text": "มีหอพักไหม", "userDefined": false}], "isTemplate": false, "count": 0, "lang": "th"}, {"id": "cd0670f0-0028-11ec-bcad-1e003136597a", "data": [{"text": "มีหอพักไหม", "userDefined": false}], "isTemplate": false, "count": 0, "lang": "th"}, {"id": "cd067172-0028-11ec-bcad-1e003136597a", "data": [{"text": "หอพักมีกี่หอคะ", "userDefined": false}], "isTemplate": false, "count": 0, "lang": "th"}, {"id": "cd0671f4-0028-11ec-bcad-1e003136597a", "data": [{"text": "มีหอพักไหม", "userDefined": false}], "isTemplate": false, "count": 0, "lang": "th"}, {"id": "cd067276-0028-11ec-bcad-1e003136597a", "data": [{"text": "มีหอพักป่าว", "userDefined": false}], "isTemplate": false, "count": 0, "lang": "th"}, {"id": "cd0672f8-0028-11ec-bcad-1e003136597a", "data": [{"text": "มีหอพักไหม", "userDefined": false}], "isTemplate": false, "count": 0, "lang": "th"}, {"id": "cd067370-0028-11ec-bcad-1e003136597a", "data": [{"text": "หอพักตั้งอยู่ตรงไหนหรอคะ", "userDefined": false}], "isTemplate": false, "count": 0, "lang": "th"}, {"id": "cd0673f2-0028-11ec-bcad-1e003136597a", "data": [{"text": "ที่มอมีหอพักไหมคะ", "userDefined": false}], "isTemplate": false, "count": 0, "lang": "th"}, {"id": "cd067474-0028-11ec-bcad-1e003136597a", "data": [{"text": "ที่มอมีหอพักไหมคะ", "userDefined": false}], "isTemplate": false, "count": 0, "lang": "th"}, {"id": "cd0674f6-0028-11ec-bcad-1e003136597a", "data": [{"text": "หอพักอยุ่ไหนคะ", "userDefined": false}], "isTemplate": false, "count": 0, "lang": "th"}]